tableread/__init__.py
tableread/writer.py
tableread-2.0.5.dist-info/WHEEL
tableread-2.0.5.dist-info/METADATA
tableread-2.0.5.dist-info/RECORD
