Metadata-Version: 2.1
Name: tableread
Version: 2.0.5
Summary: Table reader for simple reStructuredText tables
Home-page: https://jolly-good-toolbelt.github.io/tableread/
License: MIT
Author: Brad Brown
Author-email: brad@bradsbrown.com
Requires-Python: >=3.6,<4.0
Classifier: License :: OSI Approved :: MIT License
Classifier: Programming Language :: Python :: 3
Classifier: Programming Language :: Python :: 3.6
Classifier: Programming Language :: Python :: 3.7
Classifier: Programming Language :: Python :: 3.8
Requires-Dist: attrs (>=16.0.0)
Project-URL: Documentation, https://jolly-good-toolbelt.github.io/tableread/
Project-URL: Repository, https://github.com/jolly-good-toolbelt/tableread
